liquid_extra/__init__.py
liquid_extra/py.typed
liquid_extra/filters/__init__.py
liquid_extra/filters/additional.py
liquid_extra/filters/array.py
liquid_extra/filters/html.py
liquid_extra/tags/__init__.py
liquid_extra/tags/if_expressions.py
liquid_extra/tags/if_not.py
liquid_extra/tags/macro.py
liquid_extra/tags/withblock.py
python_liquid_extra-1.1.1.dist-info/LICENSE
python_liquid_extra-1.1.1.dist-info/METADATA
python_liquid_extra-1.1.1.dist-info/WHEEL
python_liquid_extra-1.1.1.dist-info/top_level.txt
python_liquid_extra-1.1.1.dist-info/RECORD
