Metadata-Version: 2.1
Name: python-liquid-extra
Version: 1.1.1
Summary: Extra tags an filters for python-liquid.
Home-page: https://github.com/jg-rp/liquid-extra
License: MIT
Project-URL: Documentation, https://jg-rp.github.io/liquid/extra/introduction
Project-URL: Issue Tracker, https://github.com/jg-rp/liquid-extra/issues
Project-URL: Source Code, https://github.com/jg-rp/liquid-extra
Project-URL: Change Log, https://github.com/jg-rp/liquid-extra/blob/main/CHANGES.rst
Classifier: Development Status :: 5 - Production/Stable
Classifier: Intended Audience :: Developers
Classifier: License :: OSI Approved :: MIT License
Classifier: Programming Language :: Python :: 3
Classifier: Programming Language :: Python :: 3.7
Classifier: Programming Language :: Python :: 3.8
Classifier: Programming Language :: Python :: 3.9
Classifier: Programming Language :: Python :: 3.10
Classifier: Programming Language :: Python :: Implementation :: CPython
Classifier: Programming Language :: Python :: Implementation :: PyPy
Requires-Python: >=3.7
License-File: LICENSE
Requires-Dist: python-liquid (>=1.2.1)
